jupyterlab_open_warning/__init__.py
jupyterlab_open_warning-0.2.0.data/data/share/jupyter/labextensions/jupyterlab-open-warning/package.json
jupyterlab_open_warning-0.2.0.data/data/share/jupyter/labextensions/jupyterlab-open-warning/static/307.d9b76eace27288be4ced.js
jupyterlab_open_warning-0.2.0.data/data/share/jupyter/labextensions/jupyterlab-open-warning/static/872.50f2c609c3373c0358d1.js
jupyterlab_open_warning-0.2.0.data/data/share/jupyter/labextensions/jupyterlab-open-warning/static/remoteEntry.003b5794ce52593ff409.js
jupyterlab_open_warning-0.2.0.data/data/share/jupyter/labextensions/jupyterlab-open-warning/static/style.js
jupyterlab_open_warning-0.2.0.data/data/share/jupyter/labextensions/jupyterlab-open-warning/static/third-party-licenses.json
jupyterlab_open_warning-0.2.0.data/data/share/jupyter/labextensions/jupyterlab-open-warning/install.json
jupyterlab_open_warning-0.2.0.dist-info/METADATA
jupyterlab_open_warning-0.2.0.dist-info/WHEEL
jupyterlab_open_warning-0.2.0.dist-info/licenses/LICENSE
jupyterlab_open_warning-0.2.0.dist-info/RECORD
